livekit/plugins/neuphonic/__init__.py
livekit/plugins/neuphonic/log.py
livekit/plugins/neuphonic/models.py
livekit/plugins/neuphonic/py.typed
livekit/plugins/neuphonic/tts.py
livekit/plugins/neuphonic/version.py
livekit_plugins_neuphonic-1.3.11.dist-info/METADATA
livekit_plugins_neuphonic-1.3.11.dist-info/WHEEL
livekit_plugins_neuphonic-1.3.11.dist-info/RECORD
