Metadata-Version: 2.4
Name: livekit-plugins-neuphonic
Version: 1.3.11
Summary: Neuphonic inference plugin for LiveKit Agents
Project-URL: Documentation, https://docs.livekit.io
Project-URL: Website, https://livekit.io/
Project-URL: Source, https://github.com/livekit/agents
Author-email: LiveKit <hello@livekit.io>
License-Expression: Apache-2.0
Keywords: ai,audio,livekit,neuphonic,realtime,video,voice
Classifier: Intended Audience :: Developers
Classifier: Programming Language :: Python :: 3
Classifier: Programming Language :: Python :: 3 :: Only
Classifier: Programming Language :: Python :: 3.11
Classifier: Programming Language :: Python :: 3.12
Classifier: Topic :: Multimedia :: Sound/Audio
Classifier: Topic :: Scientific/Engineering :: Artificial Intelligence
Requires-Python: >=3.9.0
Requires-Dist: livekit-agents>=1.3.11
